genre/__init__.py
genre/genre.py
genre-0.1.1.dist-info/LICENSE
genre-0.1.1.dist-info/METADATA
genre-0.1.1.dist-info/WHEEL
genre-0.1.1.dist-info/entry_points.txt
genre-0.1.1.dist-info/top_level.txt
genre-0.1.1.dist-info/RECORD
